<?xml version="1.0" encoding="utf-8" ?>
<Defs>

	<!--
					<NegotiationAbility>0.35</NegotiationAbility>
          			<TradePriceImprovement>0.20</TradePriceImprovement>
          			<SocialImpact>0.25</SocialImpact>
					<TameAnimalChance>0.2</TameAnimalChance>
					<TrainAnimalChance>0.2</TrainAnimalChance>
					<ConstructSuccessChance>0.2</ConstructSuccessChance>
					<MiningSpeed>0.5</MiningSpeed>
					<MiningYield>0.5</MiningYield>
				-->
	

	<HediffDef ParentName="ImplantHediffBase">
		<defName>EVOR_Hediff_Brain_Hyper</defName>
		<label>neural hyperthreader</label>
		<defaultLabelColor>(.2,1,.9)</defaultLabelColor>
		<labelNoun>neural hyperthreader</labelNoun>
		<spawnThingOnRemoved>EVOR_Item_Brain_Hyper</spawnThingOnRemoved>
		<addedPartProps>
			<solid>true</solid>
			<partEfficiency>1.0</partEfficiency>
			<betterThanNatural>true</betterThanNatural>
		</addedPartProps>
		<stages>
			<li>
				<capMods>
					<li>
						<capacity>Consciousness</capacity>
						<offset>0.25</offset>
					</li>
				</capMods>
				<restFallFactor>0.80</restFallFactor>
				<statOffsets>
					<GlobalLearningFactor>0.20</GlobalLearningFactor>
					<MentalBreakThreshold>-0.25</MentalBreakThreshold>
					<WorkSpeedGlobal>0.25</WorkSpeedGlobal>
					<ResearchSpeed>0.15</ResearchSpeed>
					<MedicalTendQuality>0.10</MedicalTendQuality>
				</statOffsets>
			</li>
		</stages>
	</HediffDef>

	<HediffDef ParentName="ImplantHediffBase">
		<defName>EVOR_Hediff_Brain_Nails</defName>
		<label>butcher's nails</label>
		<defaultLabelColor>(.2,1,.9)</defaultLabelColor>
		<labelNoun>butcher's nails</labelNoun>
		<spawnThingOnRemoved>EVOR_Item_Brain_Nails</spawnThingOnRemoved>
		<addedPartProps>
			<solid>true</solid>
			<partEfficiency>1.0</partEfficiency>
			<betterThanNatural>true</betterThanNatural>
		</addedPartProps>
		<stages>
			<li>
				<socialFightChanceFactor>10</socialFightChanceFactor>
				<mentalStateGivers>
					<li>
						<mentalState>Berserk</mentalState>
						<mtbDays>6</mtbDays>
					</li>
				</mentalStateGivers>
				<statOffsets>
					<MeleeDodgeChance>10</MeleeDodgeChance>
					<MeleeHitChance>10</MeleeHitChance>
					<MeleeWeapon_CooldownMultiplier>-.3</MeleeWeapon_CooldownMultiplier>
					<MentalBreakThreshold>0.05</MentalBreakThreshold>
					<NegotiationAbility>-1.5</NegotiationAbility>
          			<SocialImpact>-1.5</SocialImpact>
					<AimingDelayFactor>-0.15</AimingDelayFactor>
				</statOffsets>
				<painFactor>0.33</painFactor>
			</li>
		</stages>
	</HediffDef>

</Defs>